{
  "project_info": {
    "project_number": "738245793547",
    "project_id": "quiz-app-86e6b",
    "storage_bucket": "quiz-app-86e6b.firebasestorage.app"
  },
  "client": [
    {
      "client_info": {
        "mobilesdk_app_id": "1:738245793547:android:ed9061a8dcd8e50016340e",
        "android_client_info": {
          "package_name": "com.example.quiz_app"
        }
      },
      "oauth_client": [],
      "api_key": [
        {
          "current_key": "AIzaSyDZwR_fINF8bLAZyiXc1P23U6cJnrIB_gU"
        }
      ],
      "services": {
        "appinvite_service": {
          "other_platform_oauth_client": []
        }
      }
    }
  ],
  "configuration_version": "1"
}